sage_notification/__init__.py
sage_notification/admin.py
sage_notification/apps.py
sage_notification/forms.py
sage_notification/helpers/__init__.py
sage_notification/helpers/choices.py
sage_notification/migrations/__init__.py
sage_notification/models.py
sage_notification/repository/__init__.py
sage_notification/repository/manager.py
sage_notification/repository/queryset.py
sage_notification/repository/service.py
sage_notification/tests.py
sage_notification/views.py
django_sage_notification-0.1.1.dist-info/LICENSE
django_sage_notification-0.1.1.dist-info/METADATA
django_sage_notification-0.1.1.dist-info/WHEEL
django_sage_notification-0.1.1.dist-info/RECORD
